LICENSE
MANIFEST.in
README.md
pyproject.toml
setup.py
probreg/__init__.py
probreg/bcpd.py
probreg/callbacks.py
probreg/cost_functions.py
probreg/cpd.py
probreg/cupy_utils.py
probreg/features.py
probreg/filterreg.py
probreg/gauss_transform.py
probreg/gaussian_filtering.py
probreg/gmmtree.py
probreg/l2dist_regs.py
probreg/log.py
probreg/math_utils.py
probreg/se3_op.py
probreg/transformation.py
probreg/version.py
probreg.egg-info/PKG-INFO
probreg.egg-info/SOURCES.txt
probreg.egg-info/dependency_links.txt
probreg.egg-info/not-zip-safe
probreg.egg-info/requires.txt
probreg.egg-info/top_level.txt
probreg/cc/gmmtree.cc
probreg/cc/gmmtree.h
probreg/cc/gmmtree_py.cc
probreg/cc/ifgt.cc
probreg/cc/ifgt.h
probreg/cc/ifgt_py.cc
probreg/cc/kabsch.cc
probreg/cc/kabsch.h
probreg/cc/kabsch_py.cc
probreg/cc/kcenter_clustering.cc
probreg/cc/kcenter_clustering.h
probreg/cc/math_utils.cc
probreg/cc/math_utils.h
probreg/cc/math_utils_py.cc
probreg/cc/permutohedral_lattice_py.cc
probreg/cc/point_to_plane.cc
probreg/cc/point_to_plane.h
probreg/cc/point_to_plane_py.cc
probreg/cc/types.h
tests/test_cpd.py
tests/test_filterreg.py
tests/test_gauss_transform.py
tests/test_gaussian_filtering.py
tests/test_math_utils.py
tests/test_point_to_plane.py
tests/test_svr.py
third_party/eigen/Eigen/Cholesky
third_party/eigen/Eigen/CholmodSupport
third_party/eigen/Eigen/Core
third_party/eigen/Eigen/Dense
third_party/eigen/Eigen/Eigen
third_party/eigen/Eigen/Eigenvalues
third_party/eigen/Eigen/Geometry
third_party/eigen/Eigen/Householder
third_party/eigen/Eigen/IterativeLinearSolvers
third_party/eigen/Eigen/Jacobi
third_party/eigen/Eigen/KLUSupport
third_party/eigen/Eigen/LU
third_party/eigen/Eigen/MetisSupport
third_party/eigen/Eigen/OrderingMethods
third_party/eigen/Eigen/PaStiXSupport
third_party/eigen/Eigen/PardisoSupport
third_party/eigen/Eigen/QR
third_party/eigen/Eigen/QtAlignedMalloc
third_party/eigen/Eigen/SPQRSupport
third_party/eigen/Eigen/SVD
third_party/eigen/Eigen/Sparse
third_party/eigen/Eigen/SparseCholesky
third_party/eigen/Eigen/SparseCore
third_party/eigen/Eigen/SparseLU
third_party/eigen/Eigen/SparseQR
third_party/eigen/Eigen/StdDeque
third_party/eigen/Eigen/StdList
