Metadata-Version: 2.1
Name: probreg
Version: 0.3.7
Summary: Probablistic point cloud resitration algorithms
Home-page: https://github.com/neka-nat/probreg
Author: neka-nat
Author-email: nekanat.stock@gmail.com
License: UNKNOWN
Platform: UNKNOWN
